quippy/__init__.py
quippy/main.py
quippy/parser.py
quippy/quipper.g
quippy/quippy_standalone.py
quippy/transformer.py
quippy-0.3.3.data/data/LICENSE
quippy-0.3.3.data/data/NOTICE
quippy-0.3.3.dist-info/METADATA
quippy-0.3.3.dist-info/RECORD
quippy-0.3.3.dist-info/WHEEL
quippy-0.3.3.dist-info/top_level.txt
quippy-0.3.3.dist-info/zip-safe
