Metadata-Version: 2.1
Name: quippy
Version: 0.3.3
Summary: A parser for the Quipper ASCII quantum circuit output format.
Home-page: https://github.com/eddieschoute/quippy
Author: Eddie Schoute
Author-email: notprovided@example.example
License: Apache 2.0
Project-URL: Quipper, https://www.mathstat.dal.ca/~selinger/quipper/
Keywords: quipper parser quantum computing
Platform: UNKNOWN
Classifier: Development Status :: 3 - Alpha
Classifier: Intended Audience :: Developers
Classifier: Intended Audience :: Science/Research
Classifier: Topic :: Scientific/Engineering
Classifier: Topic :: Software Development :: Compilers
Classifier: License :: OSI Approved :: Apache Software License
Classifier: Programming Language :: Python :: 3.5
Classifier: Programming Language :: Python :: 3.6
Requires-Python: >=3.5,<4
Requires-Dist: lark-parser (<0.6,>=0.5.5)
